juancobo6_marco_polo/__init__.py
juancobo6_marco_polo/marco_polo.py
juancobo6_marco_polo/py.typed
juancobo6_marco_polo-0.2.1.dist-info/METADATA
juancobo6_marco_polo-0.2.1.dist-info/WHEEL
juancobo6_marco_polo-0.2.1.dist-info/top_level.txt
juancobo6_marco_polo-0.2.1.dist-info/RECORD
